mcp_serverz/__init__.py
mcp_serverz/core.py
mcp_serverz/log.py
mcp_serverz/server.py
mcp_serverz-0.1.1.dist-info/METADATA
mcp_serverz-0.1.1.dist-info/WHEEL
mcp_serverz-0.1.1.dist-info/top_level.txt
mcp_serverz-0.1.1.dist-info/RECORD
